pypjlink/__init__.py
pypjlink/cli.py
pypjlink/cliutils.py
pypjlink/projector.py
pypjlink/protocol.py
pypjlink2/__init__.py
pypjlink2/cli.py
pypjlink2/cliutils.py
pypjlink2/projector.py
pypjlink2/protocol.py
pypjlink2_rechner-1.2.2.dist-info/LICENSE
pypjlink2_rechner-1.2.2.dist-info/METADATA
pypjlink2_rechner-1.2.2.dist-info/WHEEL
pypjlink2_rechner-1.2.2.dist-info/entry_points.txt
pypjlink2_rechner-1.2.2.dist-info/top_level.txt
pypjlink2_rechner-1.2.2.dist-info/RECORD
