Metadata-Version: 2.1
Name: pypjlink2-rechner
Version: 1.2.2
Summary: PJLink is a standard for controlling data projectors.
Home-page: https://github.com/rechner/pypjlink
Author: Peter Ward <peteraward@gmail.com>, Gaetano Guerriero <gaetano.guerriero@spacespa.it>, Benoit Louy <pypjlink@mm.st>
Author-email: pypjlink@mm.st
License: UNKNOWN
Platform: UNKNOWN
Classifier: Development Status :: 5 - Production/Stable
Classifier: Environment :: Console
Classifier: License :: OSI Approved :: Apache Software License
Classifier: Natural Language :: English
Classifier: Topic :: Multimedia :: Video :: Display
Classifier: Topic :: Utilities
Requires-Dist: appdirs
